odoo/addons/account_multi_vat_sale/README.rst
odoo/addons/account_multi_vat_sale/__init__.py
odoo/addons/account_multi_vat_sale/__manifest__.py
odoo/addons/account_multi_vat_sale/i18n/account_multi_vat_sale.pot
odoo/addons/account_multi_vat_sale/i18n/fr.po
odoo/addons/account_multi_vat_sale/models/__init__.py
odoo/addons/account_multi_vat_sale/models/account_move.py
odoo/addons/account_multi_vat_sale/models/sale_order.py
odoo/addons/account_multi_vat_sale/readme/CONFIGURATION.rst
odoo/addons/account_multi_vat_sale/readme/CONTRIBUTORS.rst
odoo/addons/account_multi_vat_sale/readme/DESCRIPTION.rst
odoo/addons/account_multi_vat_sale/report/sale_order_report.xml
odoo/addons/account_multi_vat_sale/static/description/icon.png
odoo/addons/account_multi_vat_sale/static/description/index.html
odoo/addons/account_multi_vat_sale/tests/__init__.py
odoo/addons/account_multi_vat_sale/tests/test_account_multi_vat_sale.py
odoo/addons/account_multi_vat_sale/views/sale_order.xml
odoo13_addon_account_multi_vat_sale-13.0.1.0.2.dist-info/METADATA
odoo13_addon_account_multi_vat_sale-13.0.1.0.2.dist-info/WHEEL
odoo13_addon_account_multi_vat_sale-13.0.1.0.2.dist-info/top_level.txt
odoo13_addon_account_multi_vat_sale-13.0.1.0.2.dist-info/RECORD
