Metadata-Version: 2.1
Name: odoo13-addon-account-multi-vat-sale
Version: 13.0.1.0.2
Summary: Determines the tax administration from the delivery address of the invoice.
Home-page: https://github.com/OCA/account-fiscal-rule
Author: ACSONE SA/NV,Odoo Community Association (OCA)
Author-email: support@odoo-community.org
License: AGPL-3
Platform: UNKNOWN
Classifier: Programming Language :: Python
Classifier: Framework :: Odoo
Classifier: Framework :: Odoo :: 13.0
Classifier: License :: OSI Approved :: GNU Affero General Public License v3
Classifier: Development Status :: 4 - Beta
Requires-Python: >=3.5
Requires-Dist: odoo13-addon-account-multi-vat
Requires-Dist: odoo (<13.1dev,>=13.0a)
